{
  "doi": "https://openalex.org/W4389548398",
  "openalex": {
    "id": "https://openalex.org/W4389548398",
    "doi": "https://doi.org/10.1097/aln.0000000000004857",
    "title": "Multicenter, Randomized, Placebo-controlled Crossover Trial Evaluating Topical Lidocaine for Mechanical Cervical Pain",
    "display_name": "Multicenter, Randomized, Placebo-controlled Crossover Trial Evaluating Topical Lidocaine for Mechanical Cervical Pain",
    "publication_year": 2023,
    "publication_date": "2023-12-11",
    "ids": {
      "openalex": "https://openalex.org/W4389548398",
      "doi": "https://doi.org/10.1097/aln.0000000000004857",
      "pmid": "https://pubmed.ncbi.nlm.nih.gov/38079112"
    },
    "language": "en",
    "primary_location": {
      "id": "doi:10.1097/aln.0000000000004857",
      "is_oa": true,
      "landing_page_url": "https://doi.org/10.1097/aln.0000000000004857",
      "pdf_url": "https://pubs.asahq.org/anesthesiology/article-pdf/doi/10.1097/ALN.0000000000004857/700365/20240300.0-00024.pdf",
      "source": {
        "id": "https://openalex.org/S124035732",
        "display_name": "Anesthesiology",
        "issn_l": "0003-3022",
        "issn": [
          "0003-3022",
          "1528-1175"
        ],
        "is_oa": false,
        "is_in_doaj": false,
        "is_core": true,
        "host_organization": "https://openalex.org/P4310315671",
        "host_organization_name": "Lippincott Williams & Wilkins",
        "host_organization_lineage": [
          "https://openalex.org/P4310315671",
          "https://openalex.org/P4310318547"
        ],
        "host_organization_lineage_names": [
          "Lippincott Williams & Wilkins",
          "Wolters Kluwer"
        ],
        "type": "journal"
      },
      "license": null,
      "license_id": null,
      "version": "publishedVersion",
      "is_accepted": true,
      "is_published": true,
      "raw_source_name": "Anesthesiology",
      "raw_type": "journal-article"
    },
    "type": "article",
    "indexed_in": [
      "crossref",
      "pubmed"
    ],
    "open_access": {
      "is_oa": true,
      "oa_status": "bronze",
      "oa_url": "https://pubs.asahq.org/anesthesiology/article-pdf/doi/10.1097/ALN.0000000000004857/700365/20240300.0-00024.pdf",
      "any_repository_has_fulltext": false
    },
    "authorships": [
      {
        "author_position": "first",
        "author": {
          "id": "https://openalex.org/A5051700311",
          "display_name": "Steven P. Cohen",
          "orcid": "https://orcid.org/0000-0001-5928-2127"
        },
        "institutions": [
          {
            "id": "https://openalex.org/I1298723799",
            "display_name": "Environmental Defense Fund",
            "ror": "https://ror.org/02tj7r959",
            "country_code": "US",
            "type": "nonprofit",
            "lineage": [
              "https://openalex.org/I1298723799"
            ]
          },
          {
            "id": "https://openalex.org/I2800363604",
            "display_name": "Walter Reed National Military Medical Center",
            "ror": "https://ror.org/025cem651",
            "country_code": "US",
            "type": "healthcare",
            "lineage": [
              "https://openalex.org/I1330347796",
              "https://openalex.org/I2800250139",
              "https://openalex.org/I2800363604",
              "https://openalex.org/I2800386880"
            ]
          },
          {
            "id": "https://openalex.org/I4210135398",
            "display_name": "Committee on Publication Ethics",
            "ror": "https://ror.org/030dw3650",
            "country_code": "GB",
            "type": "nonprofit",
            "lineage": [
              "https://openalex.org/I4210135398"
            ]
          },
          {
            "id": "https://openalex.org/I145311948",
            "display_name": "Johns Hopkins University",
            "ror": "https://ror.org/00za53h95",
            "country_code": "US",
            "type": "education",
            "lineage": [
              "https://openalex.org/I145311948"
            ]
          },
          {
            "id": "https://openalex.org/I194629146",
            "display_name": "School of the Art Institute of Chicago",
            "ror": "https://ror.org/04dh2y609",
            "country_code": "US",
            "type": "education",
            "lineage": [
              "https://openalex.org/I194629146"
            ]
          }
        ],
        "countries": [
          "GB",
          "US"
        ],
        "is_corresponding": true,
        "raw_author_name": "Steven P. Cohen",
        "raw_affiliation_strings": [
          "Department of Anesthesiology, Pain Medicine Division and Departments of Physical Medicine and Rehabilitation, Neurology, Psychiatry and Neurosurgery, Northwestern Feinberg School of Medicine, Chicago, Illinois; Departments of Anesthesiology and Physical Medicine and Rehabilitation, Walter Reed National Military Medical Center, Uniformed Services University of the Health Sciences, Bethesda, Maryland",
          "Submitted for publication August 29, 2023. Accepted for publication November 28, 2023. Published online first on December 11, 2023",
          "The article processing fee was funded jointly by the U.S. Department of Defense and Scilex",
          "1Departments of Anesthesiology, Neurology, Physical Medicine & Rehabilitation and Psychiatry and Behavioral Sciences, Johns Hopkins School of Medicine, Baltimore, Maryland; Departments of Anesthesiology, Neurology, Physical Medicine & Rehabilitation, Psychiatry, and Neurosurgery, Northwestern University Feinberg School of Medicine, Chicago, Illinois; Departments of Physical Medicine & Rehabilitation and Anesthesiology, Walter Reed National Military Medical Center, Uniformed Services University of the Health Sciences, Bethesda, Maryland",
          "Supplemental Digital Content is available for this article. Direct URL citations appear in the printed text and are available in both the HTML and PDF versions of this article. Links to the digital files are provided in the HTML text of this article on the Journal's Web site ()"
        ],
        "affiliations": [
          {
            "raw_affiliation_string": "Department of Anesthesiology, Pain Medicine Division and Departments of Physical Medicine and Rehabilitation, Neurology, Psychiatry and Neurosurgery, Northwestern Feinberg School of Medicine, Chicago, Illinois; Departments of Anesthesiology and Physical Medicine and Rehabilitation, Walter Reed National Military Medical Center, Uniformed Services University of the Health Sciences, Bethesda, Maryland",
            "institution_ids": [
              "https://openalex.org/I2800363604"
            ]
          },
          {
            "raw_affiliation_string": "Submitted for publication August 29, 2023. Accepted for publication November 28, 2023. Published online first on December 11, 2023",
            "institution_ids": [
              "https://openalex.org/I4210135398"
            ]
          },
          {
            "raw_affiliation_string": "The article processing fee was funded jointly by the U.S. Department of Defense and Scilex",
            "institution_ids": [
              "https://openalex.org/I1298723799"
            ]
          },
          {
            "raw_affiliation_string": "1Departments of Anesthesiology, Neurology, Physical Medicine & Rehabilitation and Psychiatry and Behavioral Sciences, Johns Hopkins School of Medicine, Baltimore, Maryland; Departments of Anesthesiology, Neurology, Physical Medicine & Rehabilitation, Psychiatry, and Neurosurgery, Northwestern University Feinberg School of Medicine, Chicago, Illinois; Departments of Physical Medicine & Rehabilitation and Anesthesiology, Walter Reed National Military Medical Center, Uniformed Services University of the Health Sciences, Bethesda, Maryland",
            "institution_ids": [
              "https://openalex.org/I145311948",
              "https://openalex.org/I2800363604"
            ]
          },
          {
            "raw_affiliation_string": "Supplemental Digital Content is available for this article. Direct URL citations appear in the printed text and are available in both the HTML and PDF versions of this article. Links to the digital files are provided in the HTML text of this article on the Journal's Web site ()",
            "institution_ids": [
              "https://openalex.org/I194629146"
            ]
          }
        ]
      },
      {
        "author_position": "middle",
        "author": {
          "id": "https://openalex.org/A5112507465",
          "display_name": "Thomas M. Larkin",
          "orcid": null
        },
        "institutions": [
          {
            "id": "https://openalex.org/I4210089693",
            "display_name": "Pain Management Institute",
            "ror": "https://ror.org/00878jj67",
            "country_code": "US",
            "type": "healthcare",
            "lineage": [
              "https://openalex.org/I4210089693"
            ]
          },
          {
            "id": "https://openalex.org/I194629146",
            "display_name": "School of the Art Institute of Chicago",
            "ror": "https://ror.org/04dh2y609",
            "country_code": "US",
            "type": "education",
            "lineage": [
              "https://openalex.org/I194629146"
            ]
          },
          {
            "id": "https://openalex.org/I1298723799",
            "display_name": "Environmental Defense Fund",
            "ror": "https://ror.org/02tj7r959",
            "country_code": "US",
            "type": "nonprofit",
            "lineage": [
              "https://openalex.org/I1298723799"
            ]
          },
          {
            "id": "https://openalex.org/I4210100747",
            "display_name": "Instituto de Geocronología y Geología Isotópica",
            "ror": "https://ror.org/014pzm971",
            "country_code": "AR",
            "type": "facility",
            "lineage": [
              "https://openalex.org/I151201029",
              "https://openalex.org/I24354313",
              "https://openalex.org/I4210100747",
              "https://openalex.org/I4210123736",
              "https://openalex.org/I4387155568"
            ]
          },
          {
            "id": "https://openalex.org/I4210135398",
            "display_name": "Committee on Publication Ethics",
            "ror": "https://ror.org/030dw3650",
            "country_code": "GB",
            "type": "nonprofit",
            "lineage": [
              "https://openalex.org/I4210135398"
            ]
          },
          {
            "id": "https://openalex.org/I4210135350",
            "display_name": "CVPath Institute",
            "ror": "https://ror.org/03gbzhd34",
            "country_code": "US",
            "type": "nonprofit",
            "lineage": [
              "https://openalex.org/I4210135350"
            ]
          }
        ],
        "countries": [
          "AR",
          "GB",
          "US"
        ],
        "is_corresponding": false,
        "raw_author_name": "Thomas M. Larkin",
        "raw_affiliation_strings": [
          "Pain Management Institute, Bethesda, Maryland, and Washington, D.C",
          "Submitted for publication August 29, 2023. Accepted for publication November 28, 2023. Published online first on December 11, 2023",
          "Supplemental Digital Content is available for this article. Direct URL citations appear in the printed text and are available in both the HTML and PDF versions of this article. Links to the digital files are provided in the HTML text of this article on the Journal's Web site ()",
          "The article processing fee was funded jointly by the U.S. Department of Defense and Scilex",
          "This article is featured in \"This Month in Anesthesiology,\" page A1",
          "2Pain Management Institute, Bethesda, Maryland, and Washington, D.C"
        ],
        "affiliations": [
          {
            "raw_affiliation_string": "Pain Management Institute, Bethesda, Maryland, and Washington, D.C",
            "institution_ids": [
              "https://openalex.org/I4210089693"
            ]
          },
          {
            "raw_affiliation_string": "Submitted for publication August 29, 2023. Accepted for publication November 28, 2023. Published online first on December 11, 2023",
            "institution_ids": [
              "https://openalex.org/I4210135398"
            ]
          },
          {
            "raw_affiliation_string": "Supplemental Digital Content is available for this article. Direct URL citations appear in the printed text and are available in both the HTML and PDF versions of this article. Links to the digital files are provided in the HTML text of this article on the Journal's Web site ()",
            "institution_ids": [
              "https://openalex.org/I194629146"
            ]
          },
          {
            "raw_affiliation_string": "The article processing fee was funded jointly by the U.S. Department of Defense and Scilex",
            "institution_ids": [
              "https://openalex.org/I1298723799"
            ]
          },
          {
            "raw_affiliation_string": "This article is featured in \"This Month in Anesthesiology,\" page A1",
            "institution_ids": [
              "https://openalex.org/I4210100747"
            ]
          },
          {
            "raw_affiliation_string": "2Pain Management Institute, Bethesda, Maryland, and Washington, D.C",
            "institution_ids": [
              "https://openalex.org/I4210135350"
            ]
          }
        ]
      },
      {
        "author_position": "middle",
        "author": {
          "id": "https://openalex.org/A5022272657",
          "display_name": "Aidan S. Weitzner",
          "orcid": "https://orcid.org/0000-0003-2191-0145"
        },
        "institutions": [
          {
            "id": "https://openalex.org/I145311948",
            "display_name": "Johns Hopkins University",
            "ror": "https://ror.org/00za53h95",
            "country_code": "US",
            "type": "education",
            "lineage": [
              "https://openalex.org/I145311948"
            ]
          },
          {
            "id": "https://openalex.org/I1298723799",
            "display_name": "Environmental Defense Fund",
            "ror": "https://ror.org/02tj7r959",
            "country_code": "US",
            "type": "nonprofit",
            "lineage": [
              "https://openalex.org/I1298723799"
            ]
          },
          {
            "id": "https://openalex.org/I4210135398",
            "display_name": "Committee on Publication Ethics",
            "ror": "https://ror.org/030dw3650",
            "country_code": "GB",
            "type": "nonprofit",
            "lineage": [
              "https://openalex.org/I4210135398"
            ]
          },
          {
            "id": "https://openalex.org/I4210100747",
            "display_name": "Instituto de Geocronología y Geología Isotópica",
            "ror": "https://ror.org/014pzm971",
            "country_code": "AR",
            "type": "facility",
            "lineage": [
              "https://openalex.org/I151201029",
              "https://openalex.org/I24354313",
              "https://openalex.org/I4210100747",
              "https://openalex.org/I4210123736",
              "https://openalex.org/I4387155568"
            ]
          },
          {
            "id": "https://openalex.org/I194629146",
            "display_name": "School of the Art Institute of Chicago",
            "ror": "https://ror.org/04dh2y609",
            "country_code": "US",
            "type": "education",
            "lineage": [
              "https://openalex.org/I194629146"
            ]
          }
        ],
        "countries": [
          "AR",
          "GB",
          "US"
        ],
        "is_corresponding": false,
        "raw_author_name": "Aidan S. Weitzner",
        "raw_affiliation_strings": [
          "Johns Hopkins School of Medicine, Baltimore, Maryland",
          "Supplemental Digital Content is available for this article. Direct URL citations appear in the printed text and are available in both the HTML and PDF versions of this article. Links to the digital files are provided in the HTML text of this article on the Journal's Web site ()",
          "This article is featured in \"This Month in Anesthesiology,\" page A1",
          "Submitted for publication August 29, 2023. Accepted for publication November 28, 2023. Published online first on December 11, 2023",
          "3Johns Hopkins School of Medicine, Baltimore, Maryland",
          "The article processing fee was funded jointly by the U.S. Department of Defense and Scilex"
        ],
        "affiliations": [
          {
            "raw_affiliation_string": "Johns Hopkins School of Medicine, Baltimore, Maryland",
            "institution_ids": [
              "https://openalex.org/I145311948"
            ]
          },
          {
            "raw_affiliation_string": "Supplemental Digital Content is available for this article. Direct URL citations appear in the printed text and are available in both the HTML and PDF versions of this article. Links to the digital files are provided in the HTML text of this article on the Journal's Web site ()",
            "institution_ids": [
              "https://openalex.org/I194629146"
            ]
          },
          {
            "raw_affiliation_string": "This article is featured in \"This Month in Anesthesiology,\" page A1",
            "institution_ids": [
              "https://openalex.org/I4210100747"
            ]
          },
          {
            "raw_affiliation_string": "Submitted for publication August 29, 2023. Accepted for publication November 28, 2023. Published online first on December 11, 2023",
            "institution_ids": [
              "https://openalex.org/I4210135398"
            ]
          },
          {
            "raw_affiliation_string": "3Johns Hopkins School of Medicine, Baltimore, Maryland",
            "institution_ids": [
              "https://openalex.org/I145311948"
            ]
          },
          {
            "raw_affiliation_string": "The article processing fee was funded jointly by the U.S. Department of Defense and Scilex",
            "institution_ids": [
              "https://openalex.org/I1298723799"
            ]
          }
        ]
      },
      {
        "author_position": "middle",
        "author": {
          "id": "https://openalex.org/A5019731266",
          "display_name": "Edward Dolomisiewicz",
          "orcid": "https://orcid.org/0009-0001-6457-0147"
        },
        "institutions": [
          {
            "id": "https://openalex.org/I4210135398",
            "display_name": "Committee on Publication Ethics",
            "ror": "https://ror.org/030dw3650",
            "country_code": "GB",
            "type": "nonprofit",
            "lineage": [
              "https://openalex.org/I4210135398"
            ]
          },
          {
            "id": "https://openalex.org/I2800363604",
            "display_name": "Walter Reed National Military Medical Center",
            "ror": "https://ror.org/025cem651",
            "country_code": "US",
            "type": "healthcare",
            "lineage": [
              "https://openalex.org/I1330347796",
              "https://openalex.org/I2800250139",
              "https://openalex.org/I2800363604",
              "https://openalex.org/I2800386880"
            ]
          },
          {
            "id": "https://openalex.org/I194629146",
            "display_name": "School of the Art Institute of Chicago",
            "ror": "https://ror.org/04dh2y609",
            "country_code": "US",
            "type": "education",
            "lineage": [
              "https://openalex.org/I194629146"
            ]
          },
          {
            "id": "https://openalex.org/I4210100747",
            "display_name": "Instituto de Geocronología y Geología Isotópica",
            "ror": "https://ror.org/014pzm971",
            "country_code": "AR",
            "type": "facility",
            "lineage": [
              "https://openalex.org/I151201029",
              "https://openalex.org/I24354313",
              "https://openalex.org/I4210100747",
              "https://openalex.org/I4210123736",
              "https://openalex.org/I4387155568"
            ]
          },
          {
            "id": "https://openalex.org/I1298723799",
            "display_name": "Environmental Defense Fund",
            "ror": "https://ror.org/02tj7r959",
            "country_code": "US",
            "type": "nonprofit",
            "lineage": [
              "https://openalex.org/I1298723799"
            ]
          }
        ],
        "countries": [
          "AR",
          "GB",
          "US"
        ],
        "is_corresponding": false,
        "raw_author_name": "Edward Dolomisiewicz",
        "raw_affiliation_strings": [
          "Department of Physical Medicine and Rehabilitation, Walter Reed National Military Medical Center, Uniformed Services University of the Health Sciences, Bethesda, Maryland",
          "This article is featured in \"This Month in Anesthesiology,\" page A1",
          "4Department of Physical Medicine and Rehabilitation, Walter Reed National Military Medical Center, Uniformed Services University of the Health Sciences, Bethesda, Maryland",
          "The article processing fee was funded jointly by the U.S. Department of Defense and Scilex",
          "Submitted for publication August 29, 2023. Accepted for publication November 28, 2023. Published online first on December 11, 2023",
          "Supplemental Digital Content is available for this article. Direct URL citations appear in the printed text and are available in both the HTML and PDF versions of this article. Links to the digital files are provided in the HTML text of this article on the Journal's Web site ()"
        ],
        "affiliations": [
          {
            "raw_affiliation_string": "Department of Physical Medicine and Rehabilitation, Walter Reed National Military Medical Center, Uniformed Services University of the Health Sciences, Bethesda, Maryland",
            "institution_ids": [
              "https://openalex.org/I2800363604"
            ]
          },
          {
            "raw_affiliation_string": "This article is featured in \"This Month in Anesthesiology,\" page A1",
            "institution_ids": [
              "https://openalex.org/I4210100747"
            ]
          },
          {
            "raw_affiliation_string": "4Department of Physical Medicine and Rehabilitation, Walter Reed National Military Medical Center, Uniformed Services University of the Health Sciences, Bethesda, Maryland",
            "institution_ids": [
              "https://openalex.org/I2800363604"
            ]
          },
          {
            "raw_affiliation_string": "The article processing fee was funded jointly by the U.S. Department of Defense and Scilex",
            "institution_ids": [
              "https://openalex.org/I1298723799"
            ]
          },
          {
            "raw_affiliation_string": "Submitted for publication August 29, 2023. Accepted for publication November 28, 2023. Published online first on December 11, 2023",
            "institution_ids": [
              "https://openalex.org/I4210135398"
            ]
          },
          {
            "raw_affiliation_string": "Supplemental Digital Content is available for this article. Direct URL citations appear in the printed text and are available in both the HTML and PDF versions of this article. Links to the digital files are provided in the HTML text of this article on the Journal's Web site ()",
            "institution_ids": [
              "https://openalex.org/I194629146"
            ]
          }
        ]
      },
      {
        "author_position": "middle",
        "author": {
          "id": "https://openalex.org/A5050587837",
          "display_name": "Eric J. Wang",
          "orcid": "https://orcid.org/0000-0002-9381-9554"
        },
        "institutions": [
          {
            "id": "https://openalex.org/I1298723799",
            "display_name": "Environmental Defense Fund",
            "ror": "https://ror.org/02tj7r959",
            "country_code": "US",
            "type": "nonprofit",
            "lineage": [
              "https://openalex.org/I1298723799"
            ]
          },
          {
            "id": "https://openalex.org/I194629146",
            "display_name": "School of the Art Institute of Chicago",
            "ror": "https://ror.org/04dh2y609",
            "country_code": "US",
            "type": "education",
            "lineage": [
              "https://openalex.org/I194629146"
            ]
          },
          {
            "id": "https://openalex.org/I2799853436",
            "display_name": "Johns Hopkins Medicine",
            "ror": "https://ror.org/037zgn354",
            "country_code": "US",
            "type": "healthcare",
            "lineage": [
              "https://openalex.org/I2799853436"
            ]
          },
          {
            "id": "https://openalex.org/I145311948",
            "display_name": "Johns Hopkins University",
            "ror": "https://ror.org/00za53h95",
            "country_code": "US",
            "type": "education",
            "lineage": [
              "https://openalex.org/I145311948"
            ]
          },
          {
            "id": "https://openalex.org/I4210135398",
            "display_name": "Committee on Publication Ethics",
            "ror": "https://ror.org/030dw3650",
            "country_code": "GB",
            "type": "nonprofit",
            "lineage": [
              "https://openalex.org/I4210135398"
            ]
          }
        ],
        "countries": [
          "GB",
          "US"
        ],
        "is_corresponding": false,
        "raw_author_name": "Eric J. Wang",
        "raw_affiliation_strings": [
          "Department of Anesthesiology and Critical Care Medicine, Pain Medicine Division, Johns Hopkins School of Medicine, Baltimore, Maryland",
          "Submitted for publication August 29, 2023. Accepted for publication November 28, 2023. Published online first on December 11, 2023",
          "5Department of Anesthesiology and Critical Care Medicine, Pain Medicine Division, Johns Hopkins School of Medicine, Baltimore, Maryland",
          "Supplemental Digital Content is available for this article. Direct URL citations appear in the printed text and are available in both the HTML and PDF versions of this article. Links to the digital files are provided in the HTML text of this article on the Journal's Web site ()",
          "The article processing fee was funded jointly by the U.S. Department of Defense and Scilex"
        ],
        "affiliations": [
          {
            "raw_affiliation_string": "Department of Anesthesiology and Critical Care Medicine, Pain Medicine Division, Johns Hopkins School of Medicine, Baltimore, Maryland",
            "institution_ids": [
              "https://openalex.org/I2799853436",
              "https://openalex.org/I145311948"
            ]
          },
          {
            "raw_affiliation_string": "Submitted for publication August 29, 2023. Accepted for publication November 28, 2023. Published online first on December 11, 2023",
            "institution_ids": [
              "https://openalex.org/I4210135398"
            ]
          },
          {
            "raw_affiliation_string": "5Department of Anesthesiology and Critical Care Medicine, Pain Medicine Division, Johns Hopkins School of Medicine, Baltimore, Maryland",
            "institution_ids": [
              "https://openalex.org/I2799853436",
              "https://openalex.org/I145311948"
            ]
          },
          {
            "raw_affiliation_string": "Supplemental Digital Content is available for this article. Direct URL citations appear in the printed text and are available in both the HTML and PDF versions of this article. Links to the digital files are provided in the HTML text of this article on the Journal's Web site ()",
            "institution_ids": [
              "https://openalex.org/I194629146"
            ]
          },
          {
            "raw_affiliation_string": "The article processing fee was funded jointly by the U.S. Department of Defense and Scilex",
            "institution_ids": [
              "https://openalex.org/I1298723799"
            ]
          }
        ]
      },
      {
        "author_position": "middle",
        "author": {
          "id": "https://openalex.org/A5029456413",
          "display_name": "Annie Hsu",
          "orcid": "https://orcid.org/0000-0003-3395-9085"
        },
        "institutions": [
          {
            "id": "https://openalex.org/I2799853436",
            "display_name": "Johns Hopkins Medicine",
            "ror": "https://ror.org/037zgn354",
            "country_code": "US",
            "type": "healthcare",
            "lineage": [
              "https://openalex.org/I2799853436"
            ]
          },
          {
            "id": "https://openalex.org/I4210135398",
            "display_name": "Committee on Publication Ethics",
            "ror": "https://ror.org/030dw3650",
            "country_code": "GB",
            "type": "nonprofit",
            "lineage": [
              "https://openalex.org/I4210135398"
            ]
          },
          {
            "id": "https://openalex.org/I1298723799",
            "display_name": "Environmental Defense Fund",
            "ror": "https://ror.org/02tj7r959",
            "country_code": "US",
            "type": "nonprofit",
            "lineage": [
              "https://openalex.org/I1298723799"
            ]
          },
          {
            "id": "https://openalex.org/I145311948",
            "display_name": "Johns Hopkins University",
            "ror": "https://ror.org/00za53h95",
            "country_code": "US",
            "type": "education",
            "lineage": [
              "https://openalex.org/I145311948"
            ]
          },
          {
            "id": "https://openalex.org/I194629146",
            "display_name": "School of the Art Institute of Chicago",
            "ror": "https://ror.org/04dh2y609",
            "country_code": "US",
            "type": "education",
            "lineage": [
              "https://openalex.org/I194629146"
            ]
          }
        ],
        "countries": [
          "GB",
          "US"
        ],
        "is_corresponding": false,
        "raw_author_name": "Annie Hsu",
        "raw_affiliation_strings": [
          "Department of Anesthesiology and Critical Care Medicine, Pain Medicine Division, Johns Hopkins School of Medicine, Baltimore, Maryland",
          "Supplemental Digital Content is available for this article. Direct URL citations appear in the printed text and are available in both the HTML and PDF versions of this article. Links to the digital files are provided in the HTML text of this article on the Journal's Web site ()",
          "The article processing fee was funded jointly by the U.S. Department of Defense and Scilex",
          "Submitted for publication August 29, 2023. Accepted for publication November 28, 2023. Published online first on December 11, 2023",
          "6Department of Anesthesiology and Critical Care Medicine, Pain Medicine Division, Johns Hopkins School of Medicine, Baltimore, Maryland"
        ],
        "affiliations": [
          {
            "raw_affiliation_string": "Department of Anesthesiology and Critical Care Medicine, Pain Medicine Division, Johns Hopkins School of Medicine, Baltimore, Maryland",
            "institution_ids": [
              "https://openalex.org/I2799853436",
              "https://openalex.org/I145311948"
            ]
          },
          {
            "raw_affiliation_string": "Supplemental Digital Content is available for this article. Direct URL citations appear in the printed text and are available in both the HTML and PDF versions of this article. Links to the digital files are provided in the HTML text of this article on the Journal's Web site ()",
            "institution_ids": [
              "https://openalex.org/I194629146"
            ]
          },
          {
            "raw_affiliation_string": "The article processing fee was funded jointly by the U.S. Department of Defense and Scilex",
            "institution_ids": [
              "https://openalex.org/I1298723799"
            ]
          },
          {
            "raw_affiliation_string": "Submitted for publication August 29, 2023. Accepted for publication November 28, 2023. Published online first on December 11, 2023",
            "institution_ids": [
              "https://openalex.org/I4210135398"
            ]
          },
          {
            "raw_affiliation_string": "6Department of Anesthesiology and Critical Care Medicine, Pain Medicine Division, Johns Hopkins School of Medicine, Baltimore, Maryland",
            "institution_ids": [
              "https://openalex.org/I2799853436",
              "https://openalex.org/I145311948"
            ]
          }
        ]
      },
      {
        "author_position": "middle",
        "author": {
          "id": "https://openalex.org/A5049651065",
          "display_name": "Mirinda Anderson-White",
          "orcid": null
        },
        "institutions": [
          {
            "id": "https://openalex.org/I2799853436",
            "display_name": "Johns Hopkins Medicine",
            "ror": "https://ror.org/037zgn354",
            "country_code": "US",
            "type": "healthcare",
            "lineage": [
              "https://openalex.org/I2799853436"
            ]
          },
          {
            "id": "https://openalex.org/I1298723799",
            "display_name": "Environmental Defense Fund",
            "ror": "https://ror.org/02tj7r959",
            "country_code": "US",
            "type": "nonprofit",
            "lineage": [
              "https://openalex.org/I1298723799"
            ]
          },
          {
            "id": "https://openalex.org/I194629146",
            "display_name": "School of the Art Institute of Chicago",
            "ror": "https://ror.org/04dh2y609",
            "country_code": "US",
            "type": "education",
            "lineage": [
              "https://openalex.org/I194629146"
            ]
          },
          {
            "id": "https://openalex.org/I4210135398",
            "display_name": "Committee on Publication Ethics",
            "ror": "https://ror.org/030dw3650",
            "country_code": "GB",
            "type": "nonprofit",
            "lineage": [
              "https://openalex.org/I4210135398"
            ]
          },
          {
            "id": "https://openalex.org/I145311948",
            "display_name": "Johns Hopkins University",
            "ror": "https://ror.org/00za53h95",
            "country_code": "US",
            "type": "education",
            "lineage": [
              "https://openalex.org/I145311948"
            ]
          }
        ],
        "countries": [
          "GB",
          "US"
        ],
        "is_corresponding": false,
        "raw_author_name": "Mirinda Anderson-White",
        "raw_affiliation_strings": [
          "Department of Anesthesiology and Critical Care Medicine, Pain Medicine Division, Johns Hopkins School of Medicine, Baltimore, Maryland",
          "Submitted for publication August 29, 2023. Accepted for publication November 28, 2023. Published online first on December 11, 2023",
          "7Department of Anesthesiology and Critical Care Medicine, Pain Medicine Division, Johns Hopkins School of Medicine, Baltimore, Maryland",
          "The article processing fee was funded jointly by the U.S. Department of Defense and Scilex",
          "Supplemental Digital Content is available for this article. Direct URL citations appear in the printed text and are available in both the HTML and PDF versions of this article. Links to the digital files are provided in the HTML text of this article on the Journal's Web site ()"
        ],
        "affiliations": [
          {
            "raw_affiliation_string": "Department of Anesthesiology and Critical Care Medicine, Pain Medicine Division, Johns Hopkins School of Medicine, Baltimore, Maryland",
            "institution_ids": [
              "https://openalex.org/I2799853436",
              "https://openalex.org/I145311948"
            ]
          },
          {
            "raw_affiliation_string": "Submitted for publication August 29, 2023. Accepted for publication November 28, 2023. Published online first on December 11, 2023",
            "institution_ids": [
              "https://openalex.org/I4210135398"
            ]
          },
          {
            "raw_affiliation_string": "7Department of Anesthesiology and Critical Care Medicine, Pain Medicine Division, Johns Hopkins School of Medicine, Baltimore, Maryland",
            "institution_ids": [
              "https://openalex.org/I2799853436",
              "https://openalex.org/I145311948"
            ]
          },
          {
            "raw_affiliation_string": "The article processing fee was funded jointly by the U.S. Department of Defense and Scilex",
            "institution_ids": [
              "https://openalex.org/I1298723799"
            ]
          },
          {
            "raw_affiliation_string": "Supplemental Digital Content is available for this article. Direct URL citations appear in the printed text and are available in both the HTML and PDF versions of this article. Links to the digital files are provided in the HTML text of this article on the Journal's Web site ()",
            "institution_ids": [
              "https://openalex.org/I194629146"
            ]
          }
        ]
      },
      {
        "author_position": "middle",
        "author": {
          "id": "https://openalex.org/A5104211716",
          "display_name": "Marin S. Smith",
          "orcid": "https://orcid.org/0009-0001-6612-2305"
        },
        "institutions": [
          {
            "id": "https://openalex.org/I4210135398",
            "display_name": "Committee on Publication Ethics",
            "ror": "https://ror.org/030dw3650",
            "country_code": "GB",
            "type": "nonprofit",
            "lineage": [
              "https://openalex.org/I4210135398"
            ]
          },
          {
            "id": "https://openalex.org/I1298723799",
            "display_name": "Environmental Defense Fund",
            "ror": "https://ror.org/02tj7r959",
            "country_code": "US",
            "type": "nonprofit",
            "lineage": [
              "https://openalex.org/I1298723799"
            ]
          },
          {
            "id": "https://openalex.org/I194629146",
            "display_name": "School of the Art Institute of Chicago",
            "ror": "https://ror.org/04dh2y609",
            "country_code": "US",
            "type": "education",
            "lineage": [
              "https://openalex.org/I194629146"
            ]
          },
          {
            "id": "https://openalex.org/I2800363604",
            "display_name": "Walter Reed National Military Medical Center",
            "ror": "https://ror.org/025cem651",
            "country_code": "US",
            "type": "healthcare",
            "lineage": [
              "https://openalex.org/I1330347796",
              "https://openalex.org/I2800250139",
              "https://openalex.org/I2800363604",
              "https://openalex.org/I2800386880"
            ]
          },
          {
            "id": "https://openalex.org/I4210100747",
            "display_name": "Instituto de Geocronología y Geología Isotópica",
            "ror": "https://ror.org/014pzm971",
            "country_code": "AR",
            "type": "facility",
            "lineage": [
              "https://openalex.org/I151201029",
              "https://openalex.org/I24354313",
              "https://openalex.org/I4210100747",
              "https://openalex.org/I4210123736",
              "https://openalex.org/I4387155568"
            ]
          }
        ],
        "countries": [
          "AR",
          "GB",
          "US"
        ],
        "is_corresponding": false,
        "raw_author_name": "Marin S. Smith",
        "raw_affiliation_strings": [
          "Department of Physical Medicine and Rehabilitation, Walter Reed National Military Medical Center, Uniformed Services University of the Health Sciences, Bethesda, Maryland; Geneva Foundation, Bethesda, Maryland",
          "Submitted for publication August 29, 2023. Accepted for publication November 28, 2023. Published online first on December 11, 2023",
          "8Department of Physical Medicine and Rehabilitation, Walter Reed National Military Medical Center, Uniformed Services University of the Health Sciences, Bethesda, Maryland; Geneva Foundation, Bethesda, Maryland",
          "The article processing fee was funded jointly by the U.S. Department of Defense and Scilex",
          "Supplemental Digital Content is available for this article. Direct URL citations appear in the printed text and are available in both the HTML and PDF versions of this article. Links to the digital files are provided in the HTML text of this article on the Journal's Web site ()",
          "This article is featured in \"This Month in Anesthesiology,\" page A1"
        ],
        "affiliations": [
          {
            "raw_affiliation_string": "Department of Physical Medicine and Rehabilitation, Walter Reed National Military Medical Center, Uniformed Services University of the Health Sciences, Bethesda, Maryland; Geneva Foundation, Bethesda, Maryland",
            "institution_ids": [
              "https://openalex.org/I2800363604"
            ]
          },
          {
            "raw_affiliation_string": "Submitted for publication August 29, 2023. Accepted for publication November 28, 2023. Published online first on December 11, 2023",
            "institution_ids": [
              "https://openalex.org/I4210135398"
            ]
          },
          {
            "raw_affiliation_string": "8Department of Physical Medicine and Rehabilitation, Walter Reed National Military Medical Center, Uniformed Services University of the Health Sciences, Bethesda, Maryland; Geneva Foundation, Bethesda, Maryland",
            "institution_ids": [
              "https://openalex.org/I2800363604"
            ]
          },
          {
            "raw_affiliation_string": "The article processing fee was funded jointly by the U.S. Department of Defense and Scilex",
            "institution_ids": [
              "https://openalex.org/I1298723799"
            ]
          },
          {
            "raw_affiliation_string": "Supplemental Digital Content is available for this article. Direct URL citations appear in the printed text and are available in both the HTML and PDF versions of this article. Links to the digital files are provided in the HTML text of this article on the Journal's Web site ()",
            "institution_ids": [
              "https://openalex.org/I194629146"
            ]
          },
          {
            "raw_affiliation_string": "This article is featured in \"This Month in Anesthesiology,\" page A1",
            "institution_ids": [
              "https://openalex.org/I4210100747"
            ]
          }
        ]
      },
      {
        "author_position": "last",
        "author": {
          "id": "https://openalex.org/A5091201626",
          "display_name": "Zirong Zhao",
          "orcid": "https://orcid.org/0000-0001-8417-841X"
        },
        "institutions": [
          {
            "id": "https://openalex.org/I4210100747",
            "display_name": "Instituto de Geocronología y Geología Isotópica",
            "ror": "https://ror.org/014pzm971",
            "country_code": "AR",
            "type": "facility",
            "lineage": [
              "https://openalex.org/I151201029",
              "https://openalex.org/I24354313",
              "https://openalex.org/I4210100747",
              "https://openalex.org/I4210123736",
              "https://openalex.org/I4387155568"
            ]
          },
          {
            "id": "https://openalex.org/I4210135398",
            "display_name": "Committee on Publication Ethics",
            "ror": "https://ror.org/030dw3650",
            "country_code": "GB",
            "type": "nonprofit",
            "lineage": [
              "https://openalex.org/I4210135398"
            ]
          },
          {
            "id": "https://openalex.org/I1298723799",
            "display_name": "Environmental Defense Fund",
            "ror": "https://ror.org/02tj7r959",
            "country_code": "US",
            "type": "nonprofit",
            "lineage": [
              "https://openalex.org/I1298723799"
            ]
          },
          {
            "id": "https://openalex.org/I194629146",
            "display_name": "School of the Art Institute of Chicago",
            "ror": "https://ror.org/04dh2y609",
            "country_code": "US",
            "type": "education",
            "lineage": [
              "https://openalex.org/I194629146"
            ]
          },
          {
            "id": "https://openalex.org/I2799886695",
            "display_name": "Veterans Health Administration",
            "ror": "https://ror.org/05eq41471",
            "country_code": "US",
            "type": "government",
            "lineage": [
              "https://openalex.org/I1322918889",
              "https://openalex.org/I2799886695"
            ]
          }
        ],
        "countries": [
          "AR",
          "GB",
          "US"
        ],
        "is_corresponding": false,
        "raw_author_name": "Zirong Zhao",
        "raw_affiliation_strings": [
          "Departments of Neurology and Internal Medicine, District of Columbia Veterans Affairs Medical Center, Washington, D.C",
          "9Departments of Neurology and Internal Medicine, District of Columbia Veterans Affairs Medical Center, Washington, D.C",
          "The article processing fee was funded jointly by the U.S. Department of Defense and Scilex",
          "Supplemental Digital Content is available for this article. Direct URL citations appear in the printed text and are available in both the HTML and PDF versions of this article. Links to the digital files are provided in the HTML text of this article on the Journal's Web site ()",
          "This article is featured in \"This Month in Anesthesiology,\" page A1",
          "Submitted for publication August 29, 2023. Accepted for publication November 28, 2023. Published online first on December 11, 2023"
        ],
        "affiliations": [
          {
            "raw_affiliation_string": "Departments of Neurology and Internal Medicine, District of Columbia Veterans Affairs Medical Center, Washington, D.C",
            "institution_ids": [
              "https://openalex.org/I2799886695"
            ]
          },
          {
            "raw_affiliation_string": "9Departments of Neurology and Internal Medicine, District of Columbia Veterans Affairs Medical Center, Washington, D.C",
            "institution_ids": [
              "https://openalex.org/I2799886695"
            ]
          },
          {
            "raw_affiliation_string": "The article processing fee was funded jointly by the U.S. Department of Defense and Scilex",
            "institution_ids": [
              "https://openalex.org/I1298723799"
            ]
          },
          {
            "raw_affiliation_string": "Supplemental Digital Content is available for this article. Direct URL citations appear in the printed text and are available in both the HTML and PDF versions of this article. Links to the digital files are provided in the HTML text of this article on the Journal's Web site ()",
            "institution_ids": [
              "https://openalex.org/I194629146"
            ]
          },
          {
            "raw_affiliation_string": "This article is featured in \"This Month in Anesthesiology,\" page A1",
            "institution_ids": [
              "https://openalex.org/I4210100747"
            ]
          },
          {
            "raw_affiliation_string": "Submitted for publication August 29, 2023. Accepted for publication November 28, 2023. Published online first on December 11, 2023",
            "institution_ids": [
              "https://openalex.org/I4210135398"
            ]
          }
        ]
      }
    ],
    "institutions": [],
    "countries_distinct_count": 3,
    "institutions_distinct_count": 9,
    "corresponding_author_ids": [
      "https://openalex.org/A5051700311"
    ],
    "corresponding_institution_ids": [
      "https://openalex.org/I1298723799",
      "https://openalex.org/I2800363604",
      "https://openalex.org/I4210135398",
      "https://openalex.org/I145311948",
      "https://openalex.org/I194629146"
    ],
    "apc_list": null,
    "apc_paid": null,
    "fwci": 0.62056234,
    "has_fulltext": true,
    "cited_by_count": 2,
    "citation_normalized_percentile": {
      "value": 0.70466275,
      "is_in_top_1_percent": false,
      "is_in_top_10_percent": false
    },
    "cited_by_percentile_year": {
      "min": 94,
      "max": 96
    },
    "biblio": {
      "volume": "140",
      "issue": "3",
      "first_page": "513",
      "last_page": "523"
    },
    "is_retracted": false,
    "is_paratext": false,
    "is_xpac": false,
    "primary_topic": {
      "id": "https://openalex.org/T10084",
      "display_name": "Musculoskeletal pain and rehabilitation",
      "score": 0.9991000294685364,
      "subfield": {
        "id": "https://openalex.org/subfields/2736",
        "display_name": "Pharmacology"
      },
      "field": {
        "id": "https://openalex.org/fields/27",
        "display_name": "Medicine"
      },
      "domain": {
        "id": "https://openalex.org/domains/4",
        "display_name": "Health Sciences"
      }
    },
    "topics": [
      {
        "id": "https://openalex.org/T10084",
        "display_name": "Musculoskeletal pain and rehabilitation",
        "score": 0.9991000294685364,
        "subfield": {
          "id": "https://openalex.org/subfields/2736",
          "display_name": "Pharmacology"
        },
        "field": {
          "id": "https://openalex.org/fields/27",
          "display_name": "Medicine"
        },
        "domain": {
          "id": "https://openalex.org/domains/4",
          "display_name": "Health Sciences"
        }
      },
      {
        "id": "https://openalex.org/T10196",
        "display_name": "Pain Mechanisms and Treatments",
        "score": 0.9945999979972839,
        "subfield": {
          "id": "https://openalex.org/subfields/2737",
          "display_name": "Physiology"
        },
        "field": {
          "id": "https://openalex.org/fields/27",
          "display_name": "Medicine"
        },
        "domain": {
          "id": "https://openalex.org/domains/4",
          "display_name": "Health Sciences"
        }
      },
      {
        "id": "https://openalex.org/T12712",
        "display_name": "Myofascial pain diagnosis and treatment",
        "score": 0.9843000173568726,
        "subfield": {
          "id": "https://openalex.org/subfields/1307",
          "display_name": "Cell Biology"
        },
        "field": {
          "id": "https://openalex.org/fields/13",
          "display_name": "Biochemistry, Genetics and Molecular Biology"
        },
        "domain": {
          "id": "https://openalex.org/domains/1",
          "display_name": "Life Sciences"
        }
      }
    ],
    "keywords": [
      {
        "id": "https://openalex.org/keywords/medicine",
        "display_name": "Medicine",
        "score": 0.934657096862793
      },
      {
        "id": "https://openalex.org/keywords/lidocaine",
        "display_name": "Lidocaine",
        "score": 0.8713324666023254
      },
      {
        "id": "https://openalex.org/keywords/placebo",
        "display_name": "Placebo",
        "score": 0.8190184235572815
      },
      {
        "id": "https://openalex.org/keywords/interquartile-range",
        "display_name": "Interquartile range",
        "score": 0.7630478143692017
      },
      {
        "id": "https://openalex.org/keywords/anesthesia",
        "display_name": "Anesthesia",
        "score": 0.7023494243621826
      },
      {
        "id": "https://openalex.org/keywords/crossover-study",
        "display_name": "Crossover study",
        "score": 0.5566196441650391
      },
      {
        "id": "https://openalex.org/keywords/randomized-controlled-trial",
        "display_name": "Randomized controlled trial",
        "score": 0.5480440258979797
      },
      {
        "id": "https://openalex.org/keywords/clinical-endpoint",
        "display_name": "Clinical endpoint",
        "score": 0.5054793357849121
      },
      {
        "id": "https://openalex.org/keywords/visual-analogue-scale",
        "display_name": "Visual analogue scale",
        "score": 0.42240530252456665
      },
      {
        "id": "https://openalex.org/keywords/neck-pain",
        "display_name": "Neck pain",
        "score": 0.4160383641719818
      },
      {
        "id": "https://openalex.org/keywords/surgery",
        "display_name": "Surgery",
        "score": 0.3106231093406677
      }
    ],
    "concepts": [
      {
        "id": "https://openalex.org/C71924100",
        "wikidata": "https://www.wikidata.org/wiki/Q11190",
        "display_name": "Medicine",
        "level": 0,
        "score": 0.934657096862793
      },
      {
        "id": "https://openalex.org/C2780149897",
        "wikidata": "https://www.wikidata.org/wiki/Q216935",
        "display_name": "Lidocaine",
        "level": 2,
        "score": 0.8713324666023254
      },
      {
        "id": "https://openalex.org/C27081682",
        "wikidata": "https://www.wikidata.org/wiki/Q269829",
        "display_name": "Placebo",
        "level": 3,
        "score": 0.8190184235572815
      },
      {
        "id": "https://openalex.org/C119060515",
        "wikidata": "https://www.wikidata.org/wiki/Q1916617",
        "display_name": "Interquartile range",
        "level": 2,
        "score": 0.7630478143692017
      },
      {
        "id": "https://openalex.org/C42219234",
        "wikidata": "https://www.wikidata.org/wiki/Q131130",
        "display_name": "Anesthesia",
        "level": 1,
        "score": 0.7023494243621826
      },
      {
        "id": "https://openalex.org/C87813604",
        "wikidata": "https://www.wikidata.org/wiki/Q1242899",
        "display_name": "Crossover study",
        "level": 4,
        "score": 0.5566196441650391
      },
      {
        "id": "https://openalex.org/C168563851",
        "wikidata": "https://www.wikidata.org/wiki/Q1436668",
        "display_name": "Randomized controlled trial",
        "level": 2,
        "score": 0.5480440258979797
      },
      {
        "id": "https://openalex.org/C203092338",
        "wikidata": "https://www.wikidata.org/wiki/Q1340863",
        "display_name": "Clinical endpoint",
        "level": 3,
        "score": 0.5054793357849121
      },
      {
        "id": "https://openalex.org/C14184104",
        "wikidata": "https://www.wikidata.org/wiki/Q1362526",
        "display_name": "Visual analogue scale",
        "level": 2,
        "score": 0.42240530252456665
      },
      {
        "id": "https://openalex.org/C2781038967",
        "wikidata": "https://www.wikidata.org/wiki/Q3567802",
        "display_name": "Neck pain",
        "level": 3,
        "score": 0.4160383641719818
      },
      {
        "id": "https://openalex.org/C141071460",
        "wikidata": "https://www.wikidata.org/wiki/Q40821",
        "display_name": "Surgery",
        "level": 1,
        "score": 0.3106231093406677
      },
      {
        "id": "https://openalex.org/C204787440",
        "wikidata": "https://www.wikidata.org/wiki/Q188504",
        "display_name": "Alternative medicine",
        "level": 2,
        "score": 0.0
      },
      {
        "id": "https://openalex.org/C142724271",
        "wikidata": "https://www.wikidata.org/wiki/Q7208",
        "display_name": "Pathology",
        "level": 1,
        "score": 0.0
      }
    ],
    "mesh": [
      {
        "descriptor_ui": "D006801",
        "descriptor_name": "Humans",
        "qualifier_ui": null,
        "qualifier_name": null,
        "is_major_topic": false
      },
      {
        "descriptor_ui": "D000779",
        "descriptor_name": "Anesthetics, Local",
        "qualifier_ui": null,
        "qualifier_name": null,
        "is_major_topic": true
      },
      {
        "descriptor_ui": "D019547",
        "descriptor_name": "Neck Pain",
        "qualifier_ui": "Q000188",
        "qualifier_name": "drug therapy",
        "is_major_topic": true
      },
      {
        "descriptor_ui": "D019547",
        "descriptor_name": "Neck Pain",
        "qualifier_ui": "Q000139",
        "qualifier_name": "chemically induced",
        "is_major_topic": true
      },
      {
        "descriptor_ui": "D018592",
        "descriptor_name": "Cross-Over Studies",
        "qualifier_ui": null,
        "qualifier_name": null,
        "is_major_topic": false
      },
      {
        "descriptor_ui": "D010147",
        "descriptor_name": "Pain Measurement",
        "qualifier_ui": null,
        "qualifier_name": null,
        "is_major_topic": false
      },
      {
        "descriptor_ui": "D008012",
        "descriptor_name": "Lidocaine",
        "qualifier_ui": null,
        "qualifier_name": null,
        "is_major_topic": false
      },
      {
        "descriptor_ui": "D016896",
        "descriptor_name": "Treatment Outcome",
        "qualifier_ui": null,
        "qualifier_name": null,
        "is_major_topic": false
      },
      {
        "descriptor_ui": "D004311",
        "descriptor_name": "Double-Blind Method",
        "qualifier_ui": null,
        "qualifier_name": null,
        "is_major_topic": false
      },
      {
        "descriptor_ui": "D000287",
        "descriptor_name": "Administration, Topical",
        "qualifier_ui": null,
        "qualifier_name": null,
        "is_major_topic": false
      },
      {
        "descriptor_ui": "D006801",
        "descriptor_name": "Humans",
        "qualifier_ui": null,
        "qualifier_name": null,
        "is_major_topic": false
      },
      {
        "descriptor_ui": "D000779",
        "descriptor_name": "Anesthetics, Local",
        "qualifier_ui": null,
        "qualifier_name": null,
        "is_major_topic": true
      },
      {
        "descriptor_ui": "D019547",
        "descriptor_name": "Neck Pain",
        "qualifier_ui": "Q000188",
        "qualifier_name": "drug therapy",
        "is_major_topic": true
      },
      {
        "descriptor_ui": "D019547",
        "descriptor_name": "Neck Pain",
        "qualifier_ui": "Q000139",
        "qualifier_name": "chemically induced",
        "is_major_topic": true
      },
      {
        "descriptor_ui": "D018592",
        "descriptor_name": "Cross-Over Studies",
        "qualifier_ui": null,
        "qualifier_name": null,
        "is_major_topic": false
      },
      {
        "descriptor_ui": "D010147",
        "descriptor_name": "Pain Measurement",
        "qualifier_ui": null,
        "qualifier_name": null,
        "is_major_topic": false
      },
      {
        "descriptor_ui": "D008012",
        "descriptor_name": "Lidocaine",
        "qualifier_ui": null,
        "qualifier_name": null,
        "is_major_topic": false
      },
      {
        "descriptor_ui": "D016896",
        "descriptor_name": "Treatment Outcome",
        "qualifier_ui": null,
        "qualifier_name": null,
        "is_major_topic": false
      },
      {
        "descriptor_ui": "D004311",
        "descriptor_name": "Double-Blind Method",
        "qualifier_ui": null,
        "qualifier_name": null,
        "is_major_topic": false
      },
      {
        "descriptor_ui": "D000287",
        "descriptor_name": "Administration, Topical",
        "qualifier_ui": null,
        "qualifier_name": null,
        "is_major_topic": false
      }
    ],
    "locations_count": 2,
    "locations": [
      {
        "id": "doi:10.1097/aln.0000000000004857",
        "is_oa": true,
        "landing_page_url": "https://doi.org/10.1097/aln.0000000000004857",
        "pdf_url": "https://pubs.asahq.org/anesthesiology/article-pdf/doi/10.1097/ALN.0000000000004857/700365/20240300.0-00024.pdf",
        "source": {
          "id": "https://openalex.org/S124035732",
          "display_name": "Anesthesiology",
          "issn_l": "0003-3022",
          "issn": [
            "0003-3022",
            "1528-1175"
          ],
          "is_oa": false,
          "is_in_doaj": false,
          "is_core": true,
          "host_organization": "https://openalex.org/P4310315671",
          "host_organization_name": "Lippincott Williams & Wilkins",
          "host_organization_lineage": [
            "https://openalex.org/P4310315671",
            "https://openalex.org/P4310318547"
          ],
          "host_organization_lineage_names": [
            "Lippincott Williams & Wilkins",
            "Wolters Kluwer"
          ],
          "type": "journal"
        },
        "license": null,
        "license_id": null,
        "version": "publishedVersion",
        "is_accepted": true,
        "is_published": true,
        "raw_source_name": "Anesthesiology",
        "raw_type": "journal-article"
      },
      {
        "id": "pmid:38079112",
        "is_oa": false,
        "landing_page_url": "https://pubmed.ncbi.nlm.nih.gov/38079112",
        "pdf_url": null,
        "source": {
          "id": "https://openalex.org/S4306525036",
          "display_name": "PubMed",
          "issn_l": null,
          "issn": null,
          "is_oa": false,
          "is_in_doaj": false,
          "is_core": false,
          "host_organization": "https://openalex.org/I1299303238",
          "host_organization_name": "National Institutes of Health",
          "host_organization_lineage": [
            "https://openalex.org/I1299303238"
          ],
          "host_organization_lineage_names": [],
          "type": "repository"
        },
        "license": null,
        "license_id": null,
        "version": "publishedVersion",
        "is_accepted": true,
        "is_published": true,
        "raw_source_name": "Anesthesiology",
        "raw_type": null
      }
    ],
    "best_oa_location": {
      "id": "doi:10.1097/aln.0000000000004857",
      "is_oa": true,
      "landing_page_url": "https://doi.org/10.1097/aln.0000000000004857",
      "pdf_url": "https://pubs.asahq.org/anesthesiology/article-pdf/doi/10.1097/ALN.0000000000004857/700365/20240300.0-00024.pdf",
      "source": {
        "id": "https://openalex.org/S124035732",
        "display_name": "Anesthesiology",
        "issn_l": "0003-3022",
        "issn": [
          "0003-3022",
          "1528-1175"
        ],
        "is_oa": false,
        "is_in_doaj": false,
        "is_core": true,
        "host_organization": "https://openalex.org/P4310315671",
        "host_organization_name": "Lippincott Williams & Wilkins",
        "host_organization_lineage": [
          "https://openalex.org/P4310315671",
          "https://openalex.org/P4310318547"
        ],
        "host_organization_lineage_names": [
          "Lippincott Williams & Wilkins",
          "Wolters Kluwer"
        ],
        "type": "journal"
      },
      "license": null,
      "license_id": null,
      "version": "publishedVersion",
      "is_accepted": true,
      "is_published": true,
      "raw_source_name": "Anesthesiology",
      "raw_type": "journal-article"
    },
    "sustainable_development_goals": [
      {
        "score": 0.8199999928474426,
        "id": "https://metadata.un.org/sdg/3",
        "display_name": "Good health and well-being"
      }
    ],
    "awards": [],
    "funders": [
      {
        "id": "https://openalex.org/F4320306078",
        "display_name": "U.S. Department of Defense",
        "ror": "https://ror.org/0447fe631"
      }
    ],
    "has_content": {
      "grobid_xml": false,
      "pdf": true
    },
    "content_urls": {
      "pdf": "https://content.openalex.org/works/W4389548398.pdf"
    },
    "referenced_works_count": 51,
    "referenced_works": [
      "https://openalex.org/W1812213724",
      "https://openalex.org/W1850821928",
      "https://openalex.org/W1937769321",
      "https://openalex.org/W1964972106",
      "https://openalex.org/W1976214008",
      "https://openalex.org/W1984833676",
      "https://openalex.org/W2003095469",
      "https://openalex.org/W2008860823",
      "https://openalex.org/W2021553431",
      "https://openalex.org/W2028610587",
      "https://openalex.org/W2042772149",
      "https://openalex.org/W2059619552",
      "https://openalex.org/W2062761028",
      "https://openalex.org/W2075069948",
      "https://openalex.org/W2094253223",
      "https://openalex.org/W2094304668",
      "https://openalex.org/W2130235475",
      "https://openalex.org/W2132094236",
      "https://openalex.org/W2141845857",
      "https://openalex.org/W2154693681",
      "https://openalex.org/W2161344815",
      "https://openalex.org/W2323275321",
      "https://openalex.org/W2396371054",
      "https://openalex.org/W2527824850",
      "https://openalex.org/W2536014004",
      "https://openalex.org/W2552402939",
      "https://openalex.org/W2554983266",
      "https://openalex.org/W2745732476",
      "https://openalex.org/W2770912923",
      "https://openalex.org/W2914053154",
      "https://openalex.org/W2916935058",
      "https://openalex.org/W2942939895",
      "https://openalex.org/W2945903352",
      "https://openalex.org/W3012416658",
      "https://openalex.org/W3013381570",
      "https://openalex.org/W3015754919",
      "https://openalex.org/W3032197212",
      "https://openalex.org/W3036124903",
      "https://openalex.org/W3106952850",
      "https://openalex.org/W3169002542",
      "https://openalex.org/W3191983451",
      "https://openalex.org/W4200146116",
      "https://openalex.org/W4205242448",
      "https://openalex.org/W4206901790",
      "https://openalex.org/W4292513415",
      "https://openalex.org/W4320923002",
      "https://openalex.org/W6688270600",
      "https://openalex.org/W6712217594",
      "https://openalex.org/W6728993702",
      "https://openalex.org/W6761465037",
      "https://openalex.org/W6786175747"
    ],
    "related_works": [
      "https://openalex.org/W1681476849",
      "https://openalex.org/W2487490720",
      "https://openalex.org/W1997971171",
      "https://openalex.org/W2064194781",
      "https://openalex.org/W2793077515",
      "https://openalex.org/W2043827057",
      "https://openalex.org/W2020623867",
      "https://openalex.org/W3149047655",
      "https://openalex.org/W2943046915",
      "https://openalex.org/W3049428259"
    ],
    "abstract_inverted_index": {
      "Background": [
        0
      ],
      "There": [
        1,
        203
      ],
      "are": [
        2
      ],
      "few": [
        3
      ],
      "efficacious": [
        4
      ],
      "treatments": [
        5,
        209
      ],
      "for": [
        6,
        15,
        28,
        46,
        86,
        166,
        176,
        210,
        223
      ],
      "mechanical": [
        7
      ],
      "neck": [
        8,
        105,
        123,
        157
      ],
      "pain,": [
        9,
        106
      ],
      "with": [
        10,
        107,
        126,
        284
      ],
      "controlled": [
        11
      ],
      "trials": [
        12
      ],
      "suggesting": [
        13
      ],
      "efficacy": [
        14
      ],
      "muscle": [
        16
      ],
      "relaxants": [
        17
      ],
      "and": [
        18,
        68,
        241,
        268,
        281
      ],
      "topical": [
        19,
        26,
        47
      ],
      "nonsteroidal": [
        20
      ],
      "anti-inflammatory": [
        21
      ],
      "drugs.": [
        22
      ],
      "Although": [
        23
      ],
      "studies": [
        24
      ],
      "evaluating": [
        25
      ],
      "lidocaine": [
        27,
        84,
        168,
        184,
        225,
        239,
        265,
        276
      ],
      "back": [
        29
      ],
      "pain": [
        30,
        124,
        158,
        218
      ],
      "have": [
        31
      ],
      "been": [
        32
      ],
      "disappointing,": [
        33
      ],
      "the": [
        34,
        39,
        136,
        144,
        149,
        152,
        167,
        196,
        224,
        238,
        244,
        250,
        271
      ],
      "more": [
        35,
        278
      ],
      "superficial": [
        36
      ],
      "location": [
        37
      ],
      "of": [
        38,
        116,
        132,
        140,
        187,
        233,
        235,
        253,
        275
      ],
      "cervical": [
        40
      ],
      "musculature": [
        41
      ],
      "suggests": [
        42,
        277
      ],
      "a": [
        43,
        54,
        92,
        108,
        114,
        129,
        190,
        214
      ],
      "possible": [
        44
      ],
      "role": [
        45
      ],
      "local": [
        48
      ],
      "anesthetics.": [
        49
      ],
      "Methods": [
        50
      ],
      "This": [
        51,
        299,
        302
      ],
      "study": [
        52
      ],
      "was": [
        53,
        100,
        160,
        221,
        255
      ],
      "randomized,": [
        55
      ],
      "double-blind,": [
        56
      ],
      "placebo-controlled": [
        57
      ],
      "crossover": [
        58
      ],
      "trial": [
        59
      ],
      "performed": [
        60
      ],
      "at": [
        61,
        117,
        127,
        143
      ],
      "four": [
        62
      ],
      "U.S.": [
        63
      ],
      "military,": [
        64
      ],
      "Veterans": [
        65
      ],
      "Administration,": [
        66
      ],
      "academic,": [
        67
      ],
      "private": [
        69
      ],
      "practice": [
        70
      ],
      "sites,": [
        71
      ],
      "in": [
        72,
        103,
        121,
        155,
        237,
        243
      ],
      "which": [
        73,
        254
      ],
      "76": [
        74
      ],
      "patients": [
        75,
        188,
        236
      ],
      "were": [
        76,
        204,
        266
      ],
      "randomized": [
        77
      ],
      "to": [
        78
      ],
      "receive": [
        79
      ],
      "either": [
        80
      ],
      "placebo": [
        81,
        177,
        197,
        245
      ],
      "followed": [
        82
      ],
      "by": [
        83
      ],
      "patch": [
        85,
        94
      ],
      "4-week": [
        87,
        145
      ],
      "intervals": [
        88
      ],
      "(group": [
        89
      ],
      "1)": [
        90
      ],
      "or": [
        91
      ],
      "lidocaine-then-placebo": [
        93
      ],
      "sequence.": [
        95
      ],
      "The": [
        96,
        262
      ],
      "primary": [
        97,
        150
      ],
      "outcome": [
        98,
        111,
        192
      ],
      "measure": [
        99
      ],
      "mean": [
        101
      ],
      "reduction": [
        102,
        115,
        154
      ],
      "average": [
        104,
        122,
        156
      ],
      "positive": [
        109,
        191
      ],
      "categorical": [
        110
      ],
      "designated": [
        112
      ],
      "as": [
        113
      ],
      "least": [
        118,
        128
      ],
      "2": [
        119
      ],
      "points": [
        120,
        134
      ],
      "coupled": [
        125
      ],
      "5-point": [
        130
      ],
      "score": [
        131,
        159
      ],
      "7": [
        133
      ],
      "on": [
        135,
        217
      ],
      "Patient": [
        137
      ],
      "Global": [
        138
      ],
      "Impression": [
        139
      ],
      "Change": [
        141
      ],
      "scale": [
        142
      ],
      "endpoint.": [
        146
      ],
      "Results": [
        147
      ],
      "For": [
        148
      ],
      "outcome,": [
        151
      ],
      "median": [
        153
      ],
      "−1.0": [
        161
      ],
      "(interquartile": [
        162,
        172
      ],
      "range,": [
        163,
        173
      ],
      "−2.0,": [
        164,
        174
      ],
      "0.0)": [
        165,
        175
      ],
      "phase": [
        169,
        198,
        226
      ],
      "versus": [
        170,
        193
      ],
      "−0.5": [
        171
      ],
      "treatment": [
        178
      ],
      "(": [
        179,
        199,
        227,
        257
      ],
      "P": [
        180,
        200,
        228,
        258
      ],
      "=": [
        181,
        201,
        229,
        259
      ],
      "0.17).": [
        182
      ],
      "During": [
        183
      ],
      "treatment,": [
        185
      ],
      "27.7%": [
        186
      ],
      "experienced": [
        189,
        247
      ],
      "14.9%": [
        194
      ],
      "during": [
        195
      ],
      "0.073).": [
        202
      ],
      "no": [
        205
      ],
      "significant": [
        206
      ],
      "differences": [
        207,
        263
      ],
      "between": [
        208
      ],
      "secondary": [
        211
      ],
      "outcomes,": [
        212
      ],
      "although": [
        213
      ],
      "carryover": [
        215
      ],
      "effect": [
        216
      ],
      "pressure": [
        219
      ],
      "threshold": [
        220
      ],
      "observed": [
        222
      ],
      "0.015).": [
        230
      ],
      "A": [
        231
      ],
      "total": [
        232
      ],
      "27.5%": [
        234
      ],
      "group": [
        240,
        246
      ],
      "20.5%": [
        242
      ],
      "minor": [
        248
      ],
      "reactions,": [
        249
      ],
      "most": [
        251
      ],
      "common": [
        252
      ],
      "pruritis": [
        256
      ],
      "0.36).": [
        260
      ],
      "Conclusions": [
        261
      ],
      "favoring": [
        264
      ],
      "small": [
        267
      ],
      "nonsignificant,": [
        269
      ],
      "but": [
        270
      ],
      "trend": [
        272
      ],
      "toward": [
        273
      ],
      "superiority": [
        274
      ],
      "aggressive": [
        279
      ],
      "phenotyping": [
        280
      ],
      "applying": [
        282
      ],
      "formulations": [
        283
      ],
      "greater": [
        285
      ],
      "penetrance": [
        286
      ],
      "may": [
        287
      ],
      "provide": [
        288
      ],
      "clinically": [
        289
      ],
      "meaningful": [
        290
      ],
      "benefit.": [
        291
      ],
      "Editor’s": [
        292
      ],
      "Perspective": [
        293
      ],
      "What": [
        294,
        301
      ],
      "We": [
        295
      ],
      "Already": [
        296
      ],
      "Know": [
        297
      ],
      "about": [
        298
      ],
      "Topic": [
        300
      ],
      "Article": [
        303
      ],
      "Tells": [
        304
      ],
      "Us": [
        305
      ],
      "That": [
        306
      ],
      "Is": [
        307
      ],
      "New": [
        308
      ]
    },
    "counts_by_year": [
      {
        "year": 2024,
        "cited_by_count": 2
      }
    ],
    "updated_date": "2026-01-27T00:41:06.130819",
    "created_date": "2025-10-10T00:00:00"
  },
  "crossref": {}
}